pynonamedomain/__init__.py
pynonamedomain/lego-helper.sh
pynonamedomain/nnd_cli.py
pynonamedomain/pynonamedomain.py
pynonamedomain-1.0.3.dist-info/COPYING
pynonamedomain-1.0.3.dist-info/METADATA
pynonamedomain-1.0.3.dist-info/WHEEL
pynonamedomain-1.0.3.dist-info/entry_points.txt
pynonamedomain-1.0.3.dist-info/top_level.txt
pynonamedomain-1.0.3.dist-info/RECORD
