Metadata-Version: 2.1
Name: pynonamedomain
Version: 1.0.3
Summary: Unofficial NonameDomain API module/client
Home-page: https://gitlab.com/slacker/pynonamedomain
License: GPLv3+
Keywords: nonamedomain nonamedomain.hu dns
Platform: UNKNOWN
Classifier: Programming Language :: Python :: 3 :: Only
Classifier: Topic :: Utilities
Classifier: Intended Audience :: System Administrators
Classifier: Environment :: Console
Classifier: Topic :: Internet :: Name Service (DNS)
Classifier: License :: OSI Approved :: GNU General Public License v3 or later (GPLv3+)
Classifier: Topic :: Software Development :: Libraries
Classifier: Intended Audience :: Developers
Classifier: Development Status :: 5 - Production/Stable
Classifier: Operating System :: OS Independent
Requires-Dist: Click
Requires-Dist: requests
Requires-Dist: tldextract
